pockyll.py
setup.cfg
setup.py
pockyll.egg-info/PKG-INFO
pockyll.egg-info/SOURCES.txt
pockyll.egg-info/dependency_links.txt
pockyll.egg-info/entry_points.txt
pockyll.egg-info/requires.txt
pockyll.egg-info/top_level.txt