Metadata-Version: 1.1
Name: pockyll
Version: 0.1.1
Summary: sync your pocket bookmarks to Jekyll linkposts
Home-page: https://github.com/mkirchner/pockyll/
Author: Marc Kirchner
Author-email: mail@marc-kirchner.de
License: MIT
Keywords: jekyll pocket blog linkpost
Platform: UNKNOWN
Classifier: Development Status :: 4 - Beta
Classifier: Intended Audience :: Developers
Classifier: Topic :: Software Development :: Build Tools
Classifier: License :: OSI Approved :: MIT License
Classifier: Programming Language :: Python :: 2
Classifier: Programming Language :: Python :: 2.6
Classifier: Programming Language :: Python :: 2.7
Classifier: Programming Language :: Python :: 3
Classifier: Programming Language :: Python :: 3.3
Classifier: Programming Language :: Python :: 3.4
Classifier: Programming Language :: Python :: 3.5
